{
  "transferencias": [
    {
      "id": "1",
      "valor": 35,
      "destino": "1212-1",
      "data": "2020-11-04T16:30:10.710Z"
    },
    {
      "id": "2",
      "valor": 40,
      "destino": "1213-1",
      "data": "2020-11-04T21:24:10.710Z"
    },
    {
      "id": "3",
      "valor": 12.5,
      "destino": "1214-1",
      "data": "2020-11-05T21:14:10.710Z"
    },
    {
      "valor": 15,
      "destino": "123",
      "data": "2022-02-22T18:52:09.501Z",
      "id": "GdTi4Cq"
    },
    {
      "valor": 15,
      "destino": "123",
      "data": "2022-02-22T18:52:36.421Z",
      "id": "QIpjTEh"
    },
    {
      "valor": 15,
      "destino": "123ae",
      "data": "2022-02-22T19:18:08.306Z",
      "id": "7CiCiNU"
    },
    {
      "valor": 15,
      "destino": "123ae",
      "data": "2022-02-22T19:18:09.649Z",
      "id": "8MSuERQ"
    },
    {
      "valor": 125,
      "destino": "123-5",
      "data": "2022-02-22T19:36:14.004Z",
      "id": "vIWORZq"
    },
    {
      "valor": 125,
      "destino": "325-2",
      "data": "2022-02-22T19:43:00.837Z",
      "id": "mKdbQJZ"
    },
    {
      "valor": 123,
      "destino": "123-1",
      "data": "2022-02-22T19:44:51.146Z",
      "id": "UyST-qb"
    },
    {
      "valor": 20000,
      "destino": "12345-2",
      "data": "2022-02-22T19:47:24.151Z",
      "id": "CiNvYSm"
    }
  ]
}